{
  "0 MonoBehaviour Base": {
    "0 PPtr<GameObject> m_GameObject": {
      "0 int m_FileID": 0,
      "0 SInt64 m_PathID": 0
    },
    "1 UInt8 m_Enabled": 1,
    "0 PPtr<MonoScript> m_Script": {
      "0 int m_FileID": 0,
      "0 SInt64 m_PathID": -3934732035171635000
    },
    "1 string m_Name": "ma_0201_11_E",
    "0 Sheet m_sheets": {
      "0 Array Array": [
        {
          "0 Sheet data": {
            "1 string m_name": "PlacementCollision",
            "0 Param m_list": {
              "0 Array Array": [
                {
                  "0 Param data": {
                    "1 string m_id": "EVENT_01",
                    "0 float m_posX": -22.2000008,
                    "0 float m_posY": 21.9400005,
                    "0 float m_posZ": -4.19999981,
                    "0 float m_rotY": 0,
                    "0 float m_scaleX": 22.3299999,
                    "0 float m_scaleY": 10,
                    "0 float m_scaleZ": 25,
                    "0 int m_type": 4
                  }
                },
                {
                  "0 Param data": {
                    "1 string m_id": "EVENT_01_POS_01",
                    "0 float m_posX": -22.2000008,
                    "0 float m_posY": 21.9400005,
                    "0 float m_posZ": -4.19999981,
                    "0 float m_rotY": 0,
                    "0 float m_scaleX": 0,
                    "0 float m_scaleY": 0,
                    "0 float m_scaleZ": 0,
                    "0 int m_type": 1
                  }
                },
                {
                  "0 Param data": {
                    "1 string m_id": "EVENT_01_POS_02",
                    "0 float m_posX": -22.2000008,
                    "0 float m_posY": 21.9400005,
                    "0 float m_posZ": -4.19999981,
                    "0 float m_rotY": 0,
                    "0 float m_scaleX": 0,
                    "0 float m_scaleY": 0,
                    "0 float m_scaleZ": 0,
                    "0 int m_type": 1
                  }
                },
                {
                  "0 Param data": {
                    "1 string m_id": "EVENT_02",
                    "0 float m_posX": 18.4400005,
                    "0 float m_posY": 28.7800007,
                    "0 float m_posZ": 52.3300018,
                    "0 float m_rotY": 0,
                    "0 float m_scaleX": 25,
                    "0 float m_scaleY": 10,
                    "0 float m_scaleZ": 15,
                    "0 int m_type": 4
                  }
                },
                {
                  "0 Param data": {
                    "1 string m_id": "EVENT_02_POS_01",
                    "0 float m_posX": 18.4400005,
                    "0 float m_posY": 28.7800007,
                    "0 float m_posZ": 52.3300018,
                    "0 float m_rotY": 0,
                    "0 float m_scaleX": 0,
                    "0 float m_scaleY": 0,
                    "0 float m_scaleZ": 0,
                    "0 int m_type": 1
                  }
                },
                {
                  "0 Param data": {
                    "1 string m_id": "EVENT_02_POS_02",
                    "0 float m_posX": 18.4400005,
                    "0 float m_posY": 28.7800007,
                    "0 float m_posZ": 52.3300018,
                    "0 float m_rotY": 0,
                    "0 float m_scaleX": 0,
                    "0 float m_scaleY": 0,
                    "0 float m_scaleZ": 0,
                    "0 int m_type": 1
                  }
                },
                {
                  "0 Param data": {
                    "1 string m_id": "EVENT_03",
                    "0 float m_posX": -18.8999996,
                    "0 float m_posY": 20.7299995,
                    "0 float m_posZ": -4.5999999,
                    "0 float m_rotY": 0,
                    "0 float m_scaleX": 25,
                    "0 float m_scaleY": 10,
                    "0 float m_scaleZ": 22,
                    "0 int m_type": 4
                  }
                },
                {
                  "0 Param data": {
                    "1 string m_id": "EVENT_03_POS_01",
                    "0 float m_posX": -18.8999996,
                    "0 float m_posY": 20.7299995,
                    "0 float m_posZ": -4.5999999,
                    "0 float m_rotY": 0,
                    "0 float m_scaleX": 0,
                    "0 float m_scaleY": 0,
                    "0 float m_scaleZ": 0,
                    "0 int m_type": 1
                  }
                },
                {
                  "0 Param data": {
                    "1 string m_id": "EVENT_03_POS_02",
                    "0 float m_posX": -18.8999996,
                    "0 float m_posY": 20.7299995,
                    "0 float m_posZ": -4.5999999,
                    "0 float m_rotY": 0,
                    "0 float m_scaleX": 0,
                    "0 float m_scaleY": 0,
                    "0 float m_scaleZ": 0,
                    "0 int m_type": 1
                  }
                },
                {
                  "0 Param data": {
                    "1 string m_id": "EVENT_04",
                    "0 float m_posX": -86,
                    "0 float m_posY": 47.0999985,
                    "0 float m_posZ": 119.5,
                    "0 float m_rotY": 0,
                    "0 float m_scaleX": 40,
                    "0 float m_scaleY": 10,
                    "0 float m_scaleZ": 30,
                    "0 int m_type": 4
                  }
                },
                {
                  "0 Param data": {
                    "1 string m_id": "EVENT_04_POS_01",
                    "0 float m_posX": -86,
                    "0 float m_posY": 47.0999985,
                    "0 float m_posZ": 119.5,
                    "0 float m_rotY": 0,
                    "0 float m_scaleX": 0,
                    "0 float m_scaleY": 0,
                    "0 float m_scaleZ": 0,
                    "0 int m_type": 1
                  }
                },
                {
                  "0 Param data": {
                    "1 string m_id": "EVENT_04_POS_02",
                    "0 float m_posX": -86,
                    "0 float m_posY": 47.0999985,
                    "0 float m_posZ": 119.5,
                    "0 float m_rotY": 0,
                    "0 float m_scaleX": 0,
                    "0 float m_scaleY": 0,
                    "0 float m_scaleZ": 0,
                    "0 int m_type": 1
                  }
                },
                {
                  "0 Param data": {
                    "1 string m_id": "EVENT_05",
                    "0 float m_posX": 94.9000015,
                    "0 float m_posY": 31.5,
                    "0 float m_posZ": 110.830002,
                    "0 float m_rotY": 0,
                    "0 float m_scaleX": 40,
                    "0 float m_scaleY": 20,
                    "0 float m_scaleZ": 25,
                    "0 int m_type": 4
                  }
                },
                {
                  "0 Param data": {
                    "1 string m_id": "EVENT_05_POS_01",
                    "0 float m_posX": 94.9000015,
                    "0 float m_posY": 31.5,
                    "0 float m_posZ": 110.830002,
                    "0 float m_rotY": 0,
                    "0 float m_scaleX": 0,
                    "0 float m_scaleY": 0,
                    "0 float m_scaleZ": 0,
                    "0 int m_type": 1
                  }
                },
                {
                  "0 Param data": {
                    "1 string m_id": "EVENT_05_POS_02",
                    "0 float m_posX": 94.9000015,
                    "0 float m_posY": 31.5,
                    "0 float m_posZ": 110.830002,
                    "0 float m_rotY": 0,
                    "0 float m_scaleX": 0,
                    "0 float m_scaleY": 0,
                    "0 float m_scaleZ": 0,
                    "0 int m_type": 1
                  }
                },
                {
                  "0 Param data": {
                    "1 string m_id": "EVENT_06",
                    "0 float m_posX": -89.0999985,
                    "0 float m_posY": 47.0999985,
                    "0 float m_posZ": 110.480003,
                    "0 float m_rotY": 0,
                    "0 float m_scaleX": 2,
                    "0 float m_scaleY": 2,
                    "0 float m_scaleZ": 2,
                    "0 int m_type": 2
                  }
                },
                {
                  "0 Param data": {
                    "1 string m_id": "EVENT_06_POS_01",
                    "0 float m_posX": -89.0999985,
                    "0 float m_posY": 47.0999985,
                    "0 float m_posZ": 110.480003,
                    "0 float m_rotY": 0,
                    "0 float m_scaleX": 0,
                    "0 float m_scaleY": 0,
                    "0 float m_scaleZ": 0,
                    "0 int m_type": 1
                  }
                },
                {
                  "0 Param data": {
                    "1 string m_id": "EVENT_06_POS_02",
                    "0 float m_posX": -89.0999985,
                    "0 float m_posY": 47.0999985,
                    "0 float m_posZ": 110.480003,
                    "0 float m_rotY": 0,
                    "0 float m_scaleX": 0,
                    "0 float m_scaleY": 0,
                    "0 float m_scaleZ": 0,
                    "0 int m_type": 1
                  }
                },
                {
                  "0 Param data": {
                    "1 string m_id": "EVENT_07",
                    "0 float m_posX": -94.8000031,
                    "0 float m_posY": 21.2000008,
                    "0 float m_posZ": 4.90999985,
                    "0 float m_rotY": 0,
                    "0 float m_scaleX": 15,
                    "0 float m_scaleY": 10,
                    "0 float m_scaleZ": 10,
                    "0 int m_type": 4
                  }
                },
                {
                  "0 Param data": {
                    "1 string m_id": "EVENT_07_POS_01",
                    "0 float m_posX": -94.8000031,
                    "0 float m_posY": 21.2000008,
                    "0 float m_posZ": 4.90999985,
                    "0 float m_rotY": 0,
                    "0 float m_scaleX": 0,
                    "0 float m_scaleY": 0,
                    "0 float m_scaleZ": 0,
                    "0 int m_type": 1
                  }
                },
                {
                  "0 Param data": {
                    "1 string m_id": "EVENT_07_POS_02",
                    "0 float m_posX": -94.8000031,
                    "0 float m_posY": 21.2000008,
                    "0 float m_posZ": 4.90999985,
                    "0 float m_rotY": 0,
                    "0 float m_scaleX": 0,
                    "0 float m_scaleY": 0,
                    "0 float m_scaleZ": 0,
                    "0 int m_type": 1
                  }
                },
                {
                  "0 Param data": {
                    "1 string m_id": "EVENT_08",
                    "0 float m_posX": -112.110001,
                    "0 float m_posY": 16.7999992,
                    "0 float m_posZ": 18.8700008,
                    "0 float m_rotY": 0,
                    "0 float m_scaleX": 10,
                    "0 float m_scaleY": 10,
                    "0 float m_scaleZ": 10,
                    "0 int m_type": 4
                  }
                },
                {
                  "0 Param data": {
                    "1 string m_id": "EVENT_09",
                    "0 float m_posX": 96.3000031,
                    "0 float m_posY": 30.8264351,
                    "0 float m_posZ": 93.6500015,
                    "0 float m_rotY": 0,
                    "0 float m_scaleX": 0,
                    "0 float m_scaleY": 0,
                    "0 float m_scaleZ": 0,
                    "0 int m_type": 1
                  }
                },
                {
                  "0 Param data": {
                    "1 string m_id": "EVENT_09_POS_01",
                    "0 float m_posX": 96.3000031,
                    "0 float m_posY": 30.8264351,
                    "0 float m_posZ": 93.6500015,
                    "0 float m_rotY": 0,
                    "0 float m_scaleX": 0,
                    "0 float m_scaleY": 0,
                    "0 float m_scaleZ": 0,
                    "0 int m_type": 1
                  }
                },
                {
                  "0 Param data": {
                    "1 string m_id": "EVENT_09_POS_02",
                    "0 float m_posX": 96.3000031,
                    "0 float m_posY": 30.8264351,
                    "0 float m_posZ": 93.6500015,
                    "0 float m_rotY": 0,
                    "0 float m_scaleX": 0,
                    "0 float m_scaleY": 0,
                    "0 float m_scaleZ": 0,
                    "0 int m_type": 1
                  }
                },
                {
                  "0 Param data": {
                    "1 string m_id": "EVENT_10",
                    "0 float m_posX": 15.1999998,
                    "0 float m_posY": 2.0999999,
                    "0 float m_posZ": -66.4000015,
                    "0 float m_rotY": 0,
                    "0 float m_scaleX": 25,
                    "0 float m_scaleY": 10,
                    "0 float m_scaleZ": 15,
                    "0 int m_type": 4
                  }
                },
                {
                  "0 Param data": {
                    "1 string m_id": "EVENT_10_POS_01",
                    "0 float m_posX": 15.1999998,
                    "0 float m_posY": 2.0999999,
                    "0 float m_posZ": -66.4000015,
                    "0 float m_rotY": 0,
                    "0 float m_scaleX": 0,
                    "0 float m_scaleY": 0,
                    "0 float m_scaleZ": 0,
                    "0 int m_type": 1
                  }
                },
                {
                  "0 Param data": {
                    "1 string m_id": "EVENT_10_POS_02",
                    "0 float m_posX": 15.1999998,
                    "0 float m_posY": 2.0999999,
                    "0 float m_posZ": -66.4000015,
                    "0 float m_rotY": 0,
                    "0 float m_scaleX": 0,
                    "0 float m_scaleY": 0,
                    "0 float m_scaleZ": 0,
                    "0 int m_type": 1
                  }
                }
              ]
            }
          }
        }
      ]
    }
  }
}